installer/linux-flatpak/generator.py
skytemple/__init__.py
skytemple/_i18n.py
skytemple/app.py
skytemple/init_locale.py
skytemple/main.py
skytemple/py.typed
skytemple/skytemple.css
skytemple/skytemple.glade
skytemple/controller/__init__.py
skytemple/controller/main.py
skytemple/controller/settings.py
skytemple/controller/tilequant_dialog.py
skytemple/core/__init__.py
skytemple/core/abstract_module.py
skytemple/core/canvas_scale.py
skytemple/core/error_handler.py
skytemple/core/img_utils.py
skytemple/core/item_tree.py
skytemple/core/list_icon_renderer.py
skytemple/core/logger.py
skytemple/core/message_dialog.py
skytemple/core/model_context.py
skytemple/core/module_controller.py
skytemple/core/modules.py
skytemple/core/open_request.py
skytemple/core/profiling.py
skytemple/core/rom_project.py
skytemple/core/sentry.py
skytemple/core/sentry_ext.py
skytemple/core/settings.py
skytemple/core/sprite_provider.py
skytemple/core/string_provider.py
skytemple/core/ui_utils.py
skytemple/core/view_loader.py
skytemple/core/async_tasks/__init__.py
skytemple/core/async_tasks/delegator.py
skytemple/core/async_tasks/now.py
skytemple/core/events/__init__.py
skytemple/core/events/abstract_listener.py
skytemple/core/events/events.py
skytemple/core/events/manager.py
skytemple/core/events/impl/__init__.py
skytemple/core/events/impl/discord.py
skytemple/core/mapbg_util/__init__.py
skytemple/core/mapbg_util/map_tileset_overlay.py
skytemple/core/mapbg_util/drawer_plugin/__init__.py
skytemple/core/mapbg_util/drawer_plugin/abstract.py
skytemple/core/mapbg_util/drawer_plugin/grid.py
skytemple/core/mapbg_util/drawer_plugin/selection.py
skytemple/core/plugin_loader/__init__.py
skytemple/core/plugin_loader/finder.py
skytemple/core/plugin_loader/loader.py
skytemple/core/ssb_debugger/__init__.py
skytemple/core/ssb_debugger/context.py
skytemple/core/ssb_debugger/manager.py
skytemple/core/ssb_debugger/ssb_loaded_file_handler.py
skytemple/core/third_party_util/__init__.py
skytemple-1.8.3.dist-info/LICENSE
skytemple-1.8.3.dist-info/METADATA
skytemple-1.8.3.dist-info/WHEEL
skytemple-1.8.3.dist-info/entry_points.txt
skytemple-1.8.3.dist-info/top_level.txt
skytemple-1.8.3.dist-info/RECORD
