Metadata-Version: 2.1
Name: skytemple
Version: 1.8.3
Summary: GUI Application to edit the ROM of Pokémon Mystery Dungeon Explorers of Sky
Author-email: "Marco \"Capypara\" Köpcke" <hello@capypara.de>
License: GPL-3.0-or-later
Project-URL: Homepage, https://skytemple.org
Project-URL: Announcements, https://blog.skytemple.org
Project-URL: Documentation, https://wiki.skytemple.org
Project-URL: Downloads, https://download.skytemple.org/skytemple
Project-URL: Changelog, https://download.skytemple.org/skytemple
Project-URL: Repository, https://github.com/SkyTemple/skytemple.git
Project-URL: Issues, https://github.com/SkyTemple/skytemple/issues
Project-URL: Discord, https://discord.gg/skytemple
Keywords: rom-hacking,game-modding,skytemple,gtk
Classifier: Development Status :: 4 - Beta
Classifier: Programming Language :: Python
Classifier: License :: OSI Approved :: GNU General Public License v3 or later (GPLv3+)
Classifier: Programming Language :: Python :: 3.9
Classifier: Programming Language :: Python :: 3.10
Classifier: Programming Language :: Python :: 3.11
Classifier: Programming Language :: Python :: 3.12
Requires-Python: >=3.9
License-File: LICENSE
Requires-Dist: ndspy >=3.0.0
Requires-Dist: skytemple-files[spritecollab] <1.9.0,>=1.8.3
Requires-Dist: pmdsky-debug-py
Requires-Dist: skytemple-dtef <1.9.0,>=1.6.1
Requires-Dist: skytemple-icons <1.7.0,>=1.3.2
Requires-Dist: range-typed-integers >=1.0.0
Requires-Dist: pygobject >=3.26.0
Requires-Dist: pycairo >=1.16.0
Requires-Dist: natsort >=7.0.0
Requires-Dist: tilequant >=1.1.0
Requires-Dist: skytemple-ssb-debugger <1.9.0,>=1.8.2
Requires-Dist: pygal >=2.4.0
Requires-Dist: CairoSVG >=2.4.2
Requires-Dist: psutil >=5.9.0
Requires-Dist: sentry-sdk >=1.5
Requires-Dist: packaging
Requires-Dist: wheel
Requires-Dist: importlib-metadata >=4.6 ; python_version < "3.10"
Provides-Extra: discord
Requires-Dist: pypresence >=4.2.1 ; extra == 'discord'
Provides-Extra: eventserver
Requires-Dist: skytemple-eventserver <1.7.0,>=1.6.0 ; extra == 'eventserver'
